{
  "attributes": [
    {
      "allow_nil?": false,
      "default": "fragment(\"uuid_generate_v7()\")",
      "generated?": false,
      "primary_key?": true,
      "references": null,
      "size": null,
      "source": "id",
      "type": "uuid"
    },
    {
      "allow_nil?": false,
      "default": "nil",
      "generated?": false,
      "primary_key?": false,
      "references": null,
      "size": null,
      "source": "name",
      "type": "text"
    },
    {
      "allow_nil?": true,
      "default": "nil",
      "generated?": false,
      "primary_key?": false,
      "references": null,
      "size": null,
      "source": "exported_at",
      "type": "utc_datetime"
    },
    {
      "allow_nil?": true,
      "default": "nil",
      "generated?": false,
      "primary_key?": false,
      "references": null,
      "size": null,
      "source": "started_at",
      "type": "utc_datetime"
    },
    {
      "allow_nil?": true,
      "default": "nil",
      "generated?": false,
      "primary_key?": false,
      "references": null,
      "size": null,
      "source": "finished_at",
      "type": "utc_datetime"
    },
    {
      "allow_nil?": true,
      "default": "nil",
      "generated?": false,
      "primary_key?": false,
      "references": null,
      "size": null,
      "source": "mapping",
      "type": "map"
    },
    {
      "allow_nil?": false,
      "default": "nil",
      "generated?": false,
      "primary_key?": false,
      "references": null,
      "size": null,
      "source": "records_query",
      "type": "map"
    },
    {
      "allow_nil?": false,
      "default": "0",
      "generated?": false,
      "primary_key?": false,
      "references": null,
      "size": null,
      "source": "exported_count",
      "type": "bigint"
    },
    {
      "allow_nil?": false,
      "default": "0",
      "generated?": false,
      "primary_key?": false,
      "references": null,
      "size": null,
      "source": "rows_count",
      "type": "bigint"
    },
    {
      "allow_nil?": false,
      "default": "\"collection_mapping\"",
      "generated?": false,
      "primary_key?": false,
      "references": null,
      "size": null,
      "source": "header_source",
      "type": "text"
    },
    {
      "allow_nil?": false,
      "default": "\"raw\"",
      "generated?": false,
      "primary_key?": false,
      "references": null,
      "size": null,
      "source": "data_layer",
      "type": "text"
    },
    {
      "allow_nil?": false,
      "default": "fragment(\"(now() AT TIME ZONE 'utc')\")",
      "generated?": false,
      "primary_key?": false,
      "references": null,
      "size": null,
      "source": "inserted_at",
      "type": "utc_datetime_usec"
    },
    {
      "allow_nil?": false,
      "default": "fragment(\"(now() AT TIME ZONE 'utc')\")",
      "generated?": false,
      "primary_key?": false,
      "references": null,
      "size": null,
      "source": "updated_at",
      "type": "utc_datetime_usec"
    },
    {
      "allow_nil?": true,
      "default": "nil",
      "generated?": false,
      "primary_key?": false,
      "references": {
        "deferrable": false,
        "destination_attribute": "id",
        "destination_attribute_default": null,
        "destination_attribute_generated": null,
        "index?": true,
        "match_type": null,
        "match_with": null,
        "multitenancy": {
          "attribute": null,
          "global": null,
          "strategy": null
        },
        "name": "exports_collection_id_fkey",
        "on_delete": "delete",
        "on_update": "update",
        "primary_key?": true,
        "schema": "public",
        "table": "collections"
      },
      "size": null,
      "source": "collection_id",
      "type": "uuid"
    },
    {
      "allow_nil?": true,
      "default": "nil",
      "generated?": false,
      "primary_key?": false,
      "references": {
        "deferrable": false,
        "destination_attribute": "id",
        "destination_attribute_default": null,
        "destination_attribute_generated": null,
        "index?": true,
        "match_type": null,
        "match_with": null,
        "multitenancy": {
          "attribute": null,
          "global": null,
          "strategy": null
        },
        "name": "exports_attachment_id_fkey",
        "on_delete": "delete",
        "on_update": "update",
        "primary_key?": true,
        "schema": "public",
        "table": "file_attachments"
      },
      "size": null,
      "source": "attachment_id",
      "type": "uuid"
    },
    {
      "allow_nil?": false,
      "default": "\"pending\"",
      "generated?": false,
      "primary_key?": false,
      "references": null,
      "size": null,
      "source": "state",
      "type": "text"
    }
  ],
  "base_filter": null,
  "check_constraints": [],
  "custom_indexes": [],
  "custom_statements": [],
  "has_create_action": true,
  "hash": "612860EA2DAD9A54080689CC61100477E28B309244F6A84C468C4E80F1D3AE64",
  "identities": [],
  "multitenancy": {
    "attribute": null,
    "global": null,
    "strategy": null
  },
  "repo": "Elixir.DataAggregator.Repo",
  "schema": null,
  "table": "exports"
}